DailyLogger/DailyLogFile.py
DailyLogger/__init__.py
RektecDailyLogger/DailyLogFile.py
RektecDailyLogger/__init__.py
RektecUUID/UUIDGenerator.py
RektecUUID/__init__.py
RektecUUID-0.1.2.dist-info/METADATA
RektecUUID-0.1.2.dist-info/WHEEL
RektecUUID-0.1.2.dist-info/top_level.txt
RektecUUID-0.1.2.dist-info/RECORD
