Metadata-Version: 2.1
Name: RektecUUID
Version: 0.1.2
Summary: Dailylogger deal for Rektec.co.
Home-page: https://github.com/yourusername/my-awesome-package
Author: cacaowang
Author-email: cacaowang@rektec.com.cn
License: MIT
Platform: UNKNOWN
Classifier: Development Status :: 3 - Alpha
Classifier: Intended Audience :: Developers
Classifier: License :: OSI Approved :: MIT License
Classifier: Programming Language :: Python
Classifier: Programming Language :: Python :: 3
Classifier: Programming Language :: Python :: 3.6
Classifier: Programming Language :: Python :: 3.7
Classifier: Programming Language :: Python :: 3.8
Classifier: Programming Language :: Python :: 3.9
Classifier: Programming Language :: Python :: 3.10
